ugot/__init__.py
ugot/ugot.py
ugot/grpc_pb/__init__.py
ugot/grpc_pb/audio_pb2.py
ugot/grpc_pb/audio_pb2_grpc.py
ugot/grpc_pb/bluetooth_pb2.py
ugot/grpc_pb/bluetooth_pb2_grpc.py
ugot/grpc_pb/device_pb2.py
ugot/grpc_pb/device_pb2_grpc.py
ugot/grpc_pb/gpio_pb2.py
ugot/grpc_pb/gpio_pb2_grpc.py
ugot/grpc_pb/model_pb2.py
ugot/grpc_pb/model_pb2_grpc.py
ugot/grpc_pb/network_pb2.py
ugot/grpc_pb/network_pb2_grpc.py
ugot/grpc_pb/power_pb2.py
ugot/grpc_pb/power_pb2_grpc.py
ugot/grpc_pb/sensor_pb2.py
ugot/grpc_pb/sensor_pb2_grpc.py
ugot/grpc_pb/servo_pb2.py
ugot/grpc_pb/servo_pb2_grpc.py
ugot/grpc_pb/vision_pb2.py
ugot/grpc_pb/vision_pb2_grpc.py
ugot/protos/__init__.py
ugot/src/PID.py
ugot/src/__init__.py
ugot/src/audio_client.py
ugot/src/base_client.py
ugot/src/bluetooth_client.py
ugot/src/configure_string_single.py
ugot/src/device_client.py
ugot/src/enum.py
ugot/src/gpio_client.py
ugot/src/http_client.py
ugot/src/model_client.py
ugot/src/network_client.py
ugot/src/power_client.py
ugot/src/scan_device.py
ugot/src/sensor_client.py
ugot/src/servo_client.py
ugot/src/util.py
ugot/src/vision_client.py
ugot/src/locale/en/LC_MESSAGES/ugot.mo
ugot/src/locale/en/LC_MESSAGES/ugot.po
ugot/src/locale/zh_CN/LC_MESSAGES/ugot.mo
ugot/src/locale/zh_CN/LC_MESSAGES/ugot.po
ugot-0.2.13.dist-info/LICENSE
ugot-0.2.13.dist-info/METADATA
ugot-0.2.13.dist-info/WHEEL
ugot-0.2.13.dist-info/top_level.txt
ugot-0.2.13.dist-info/RECORD
